{
  "ButtonAdd": "追加",
  "ButtonAddApiKey": "APIキーの追加",
  "ButtonAddChapters": "チャプターの追加",
  "ButtonAddDevice": "端末の追加",
  "ButtonAddLibrary": "ライブラリーの追加",
  "ButtonAddPodcasts": "ポッドキャストの追加",
  "ButtonAddUser": "ユーザーの追加",
  "ButtonAddYourFirstLibrary": "最初のライブラリーを追加",
  "ButtonApply": "確定",
  "ButtonApplyChapters": "チャプターを確定する",
  "ButtonAuthors": "作者",
  "ButtonBack": "戻る",
  "ButtonBatchEditPopulateFromExisting": "既存のものから取り込む",
  "ButtonBatchEditPopulateMapDetails": "チャプター情報を読み込む",
  "ButtonBrowseForFolder": "フォルダーを選択する",
  "ButtonCancel": "キャンセル",
  "ButtonCancelEncode": "エンコードを取り消す",
  "ButtonChangeRootPassword": "ルートのパスワードを変更する",
  "ButtonCheckAndDownloadNewEpisodes": "新しいエピソードを確認してダウンロード",
  "ButtonChooseAFolder": "フォルダーを選ぶ",
  "ButtonChooseFiles": "ファイルを選ぶ",
  "ButtonClearFilter": "絞り込みを解除",
  "ButtonClose": "閉じる",
  "ButtonCloseFeed": "フィードを閉じる",
  "ButtonCloseSession": "開いているセッションを閉じる",
  "ButtonCollections": "コレクション",
  "ButtonConfigureScanner": "スキャナーの設定",
  "ButtonCreate": "作成",
  "ButtonCreateBackup": "バックアップを作成する",
  "ButtonDelete": "削除",
  "ButtonDownloadQueue": "ダウンロードキュー",
  "ButtonEdit": "編集",
  "ButtonEditChapters": "チャプターの編集",
  "ButtonEditPodcast": "ポッドキャストの編集",
  "ButtonEnable": "オンにする",
  "ButtonFireAndFail": "エラーを無視して実行",
  "ButtonFireOnTest": "テストを実行",
  "ButtonForceReScan": "強制的に再スキャンする",
  "ButtonFullPath": "絶対パス",
  "ButtonHide": "非表示",
  "ButtonHome": "ホーム",
  "ButtonIssues": "問題",
  "ButtonJumpBackward": "巻き戻し",
  "ButtonJumpForward": "早送り",
  "ButtonLatest": "最新",
  "ButtonLibrary": "ライブラリー",
  "ButtonLogout": "ログアウト",
  "ButtonLookup": "参照",
  "ButtonManageTracks": "トラックの管理",
  "ButtonMapChapterTitles": "チャプターのタイトルを割り当て",
  "ButtonMatchAllAuthors": "すべての作者と紐付け",
  "ButtonMatchBooks": "本と紐付け",
  "ButtonNevermind": "中止",
  "ButtonNext": "次へ",
  "ButtonNextChapter": "次のチャプター",
  "ButtonNextItemInQueue": "キューにある次のアイテム",
  "ButtonOk": "はい",
  "ButtonOpenFeed": "フィードを開く",
  "ButtonOpenManager": "管理画面を開く",
  "ButtonPause": "一時停止",
  "ButtonPlay": "再生",
  "ButtonPlayAll": "全て再生",
  "ButtonPlaying": "プレイ中",
  "ButtonPlaylists": "プレイリスト",
  "ButtonPrevious": "前へ",
  "ButtonPreviousChapter": "前のチャプター",
  "ButtonProbeAudioFile": "オーディオファイルを解析",
  "ButtonPurgeAllCache": "全てのキャッシュを削除",
  "ButtonPurgeItemsCache": "項目のキャッシュを削除",
  "ButtonQueueAddItem": "次に再生する",
  "ButtonQueueRemoveItem": "「次に再生」から削除",
  "ButtonQuickEmbed": "クイック埋め込み",
  "ButtonQuickEmbedMetadata": "メタデータの埋め込み",
  "ButtonQuickMatch": "クイックマッチ",
  "ButtonReScan": "再スキャン",
  "ButtonRead": "読む",
  "ButtonReadLess": "少なく表示",
  "ButtonReadMore": "もっと見る",
  "ButtonRefresh": "再読み込み",
  "ButtonRemove": "削除",
  "ButtonRemoveAll": "全て削除",
  "ButtonRemoveAllLibraryItems": "ライブラリーの項目を全て削除",
  "ButtonRemoveFromContinueListening": "「続きを聴く」から削除",
  "ButtonRemoveFromContinueReading": "「続きを読む」から削除",
  "ButtonRemoveSeriesFromContinueSeries": "「シリーズを続ける」からシリーズを削除",
  "ButtonReset": "元に戻す",
  "ButtonResetToDefault": "デフォルトに戻す",
  "ButtonRestore": "復元",
  "ButtonSave": "保存",
  "ButtonSaveAndClose": "保存して閉じる",
  "ButtonSaveTracklist": "トラックリストを保存",
  "ButtonScan": "スキャン",
  "ButtonScanLibrary": "ライブラリーをスキャン",
  "ButtonScrollLeft": "左にスクロール",
  "ButtonScrollRight": "右にスクロール",
  "ButtonSearch": "検索",
  "ButtonSelectFolderPath": "保存先フォルダを選択",
  "ButtonSeries": "シリーズ",
  "ButtonSetChaptersFromTracks": "トラックからチャプターを設定する",
  "ButtonShare": "共有",
  "ButtonShiftTimes": "再生時間の移動",
  "ButtonShow": "表示",
  "ButtonStartM4BEncode": "M4Bエンコード開始",
  "ButtonStartMetadataEmbed": "メタデータ埋め込み開始",
  "ButtonStats": "統計",
  "ButtonSubmit": "送信",
  "ButtonTest": "テスト",
  "ButtonUnlinkOpenId": "OpenID 連携解除",
  "ButtonUpload": "アップロード",
  "ButtonUploadBackup": "バックアップをアップロード",
  "ButtonUploadCover": "カバー画像をアップロード",
  "ButtonUploadOPMLFile": "OPMLファイルをアップロード",
  "ButtonUserDelete": "ユーザーを削除 {0}",
  "ButtonUserEdit": "ユーザーを編集 {0}",
  "ButtonViewAll": "すべて表示",
  "ButtonYes": "はい",
  "ErrorUploadFetchMetadataAPI": "メタデータの取得中にエラーが発生しました",
  "ErrorUploadFetchMetadataNoResults": "メタデータの取得に失敗しました。タイトルや作者名を更新してください",
  "ErrorUploadLacksTitle": "タイトルは必須です",
  "HeaderAccount": "アカウント",
  "HeaderAddCustomMetadataProvider": "カスタムメタデータプロバイダーを追加",
  "HeaderAdvanced": "上級者向け",
  "HeaderApiKeys": "APIキー",
  "HeaderAppriseNotificationSettings": "Apprise 通知設定",
  "HeaderAudioTracks": "オーディオトラック",
  "HeaderAudiobookTools": "オーディオブックのファイル管理ツール",
  "HeaderAuthentication": "認証",
  "HeaderBackups": "バックアップ",
  "HeaderBulkChapterModal": "チャプターをまとめて追加",
  "HeaderChangePassword": "パスワードを変更",
  "HeaderChapters": "チャプター",
  "HeaderChooseAFolder": "フォルダを選択",
  "HeaderCollection": "コレクション",
  "HeaderCollectionItems": "コレクションの項目",
  "HeaderCover": "カバー",
  "HeaderCurrentDownloads": "現在のダウンロード",
  "HeaderCustomMessageOnLogin": "ログイン時のカスタムメッセージ",
  "HeaderCustomMetadataProviders": "カスタムメタデータプロバイダー",
  "HeaderDetails": "詳細",
  "HeaderDownloadQueue": "ダウンロード待ち",
  "HeaderEbookFiles": "電子書籍ファイル",
  "HeaderEmail": "メール",
  "HeaderEmailSettings": "メール設定",
  "HeaderEpisodes": "エピソード",
  "HeaderEreaderDevices": "電子書籍リーダー端末",
  "HeaderEreaderSettings": "電子書籍リーダーの設定",
  "HeaderFiles": "ファイル",
  "HeaderFindChapters": "チャプターを検索",
  "HeaderIgnoredFiles": "無視されたファイル",
  "HeaderItemFiles": "アイテムファイル",
  "HeaderItemMetadataUtils": "アイテムメタデータユーティリティ",
  "HeaderLastListeningSession": "直近の再生セッション",
  "HeaderLatestEpisodes": "最新のエピソード",
  "HeaderLibraries": "ライブラリー",
  "HeaderLibraryFiles": "ライブラリーファイル",
  "HeaderLibraryStats": "ライブラリー統計",
  "HeaderListeningSessions": "再生セッション",
  "HeaderListeningStats": "再生統計",
  "HeaderLogin": "ログイン",
  "HeaderLogs": "ログ",
  "HeaderManageGenres": "ジャンルを管理",
  "HeaderManageTags": "タグを管理",
  "HeaderMapDetails": "マップの詳細",
  "HeaderMatch": "マッチ",
  "HeaderMetadataOrderOfPrecedence": "メタデータの優先順",
  "HeaderMetadataToEmbed": "埋め込むメタデータ",
  "HeaderNewAccount": "新規アカウント",
  "HeaderNewApiKey": "新規APIキー",
  "HeaderNewLibrary": "新規ライブラリー",
  "HeaderNotificationCreate": "通知を作成",
  "HeaderNotificationUpdate": "通知を更新",
  "HeaderNotifications": "通知",
  "HeaderOpenIDConnectAuthentication": "OpenID Connect 認証",
  "HeaderOpenListeningSessions": "再生中のセッション",
  "HeaderOpenRSSFeed": "RSS Feedを開く",
  "HeaderOtherFiles": "その他のファイル",
  "HeaderPasswordAuthentication": "パスワード認証",
  "HeaderPermissions": "権限",
  "HeaderPlayerQueue": "次に再生",
  "HeaderPlayerSettings": "プレーヤーの設定",
  "HeaderPlaylist": "プレイリスト",
  "HeaderPlaylistItems": "プレイリストアイテム",
  "HeaderPodcastsToAdd": "追加するポッドキャスト",
  "HeaderPresets": "プリセット",
  "HeaderPreviewCover": "カバープレビュー",
  "HeaderRSSFeedGeneral": "RSS 詳細",
  "HeaderRSSFeedIsOpen": "RSSフィードが開いています",
  "HeaderRSSFeeds": "RSSフィード",
  "HeaderRemoveEpisode": "エピソードを削除",
  "HeaderRemoveEpisodes": "{0}個のエピソードを削除",
  "HeaderSavedMediaProgress": "保存済みメディア進捗",
  "HeaderSchedule": "スケジュール",
  "HeaderScheduleEpisodeDownloads": "エピソード自動ダウンロードスケジュール",
  "HeaderScheduleLibraryScans": "ライブラリー自動スキャンスケジュール",
  "HeaderSession": "セッション",
  "HeaderSetBackupSchedule": "バックアップスケジュールの設定",
  "HeaderSettings": "設定",
  "HeaderSettingsDisplay": "表示",
  "HeaderSettingsExperimental": "実験的な機能",
  "HeaderSettingsGeneral": "一般",
  "HeaderSettingsScanner": "スキャナー",
  "HeaderSettingsSecurity": "セキュリティ",
  "HeaderSettingsWebClient": "Webクライアント",
  "HeaderSleepTimer": "スリープタイマー",
  "HeaderStatsLargestItems": "最大のアイテム",
  "HeaderStatsLongestItems": "最長のアイテム(時間)",
  "HeaderStatsMinutesListeningChart": "過去7日間のリスニング時間(分)",
  "HeaderStatsRecentSessions": "最近の再生履歴",
  "HeaderStatsTop10Authors": "上位10作者",
  "HeaderStatsTop5Genres": "上位5ジャンル",
  "HeaderTableOfContents": "目次",
  "HeaderTools": "ツール",
  "HeaderUpdateAccount": "アカウントの更新",
  "HeaderUpdateApiKey": "APIキーの更新",
  "HeaderUpdateAuthor": "作者の更新",
  "HeaderUpdateDetails": "詳細の更新",
  "HeaderUpdateLibrary": "ライブラリーの更新",
  "HeaderUsers": "ユーザー",
  "HeaderYearReview": "{0}年の振り返り",
  "HeaderYourStats": "再生統計",
  "LabelAbridged": "要約版",
  "LabelAbridgedChecked": "要約版(チェック済み)",
  "LabelAbridgedUnchecked": "完全版(未チェック)",
  "LabelAccessibleBy": "アクセス可能なユーザー",
  "LabelAccountType": "アカウントの種類",
  "LabelAccountTypeAdmin": "管理者",
  "LabelAccountTypeGuest": "ゲスト",
  "LabelAccountTypeUser": "ユーザー",
  "LabelActivities": "アクティビティー",
  "LabelActivity": "アクティビティー",
  "LabelAddToCollection": "コレクションに追加",
  "LabelAddToCollectionBatch": "コレクションに{0}冊追加",
  "LabelAddToPlaylist": "プレイリストの追加",
  "LabelAddToPlaylistBatch": "プレイリストに{0}件追加",
  "LabelAddedAt": "追加日時",
  "LabelAddedDate": "追加日時 {0}",
  "LabelAdminUsersOnly": "管理者ユーザーのみ",
  "LabelAll": "すべて",
  "LabelAllEpisodesDownloaded": "すべてのエピソードをダウンロード済み",
  "LabelAllUsers": "すべてのユーザー",
  "LabelAllUsersExcludingGuests": "ゲストを除くすべてのユーザー",
  "LabelAllUsersIncludingGuests": "ゲストを含むすべてのユーザー",
  "LabelAlreadyInYourLibrary": "すでにライブラリーにあります",
  "LabelApiKeyCreated": "APIキー \"{0}\" が正常に作成されました。",
  "LabelApiKeyCreatedDescription": "このAPIキーを今すぐコピーしてください。二度と確認できません。",
  "LabelApiKeyUser": "ユーザーの代わりに動作",
  "LabelApiKeyUserDescription": "このAPIキーは代わりに動作するユーザーと同じ権限を持ちます。ログではユーザーがリクエストを行っているのと同じように表示されます。",
  "LabelApiToken": "APIトークン",
  "LabelAppend": "追記",
  "LabelAudioBitrate": "オーディオビットレート(例: 128k)",
  "LabelAudioChannels": "オーディオチャンネル(1または2)",
  "LabelAudioCodec": "オーディオコーデック",
  "LabelAuthor": "作者",
  "LabelAuthorFirstLast": "作者(名 氏)",
  "LabelAuthorLastFirst": "作者(氏 名)",
  "LabelAuthors": "作者",
  "LabelAutoDownloadEpisodes": "エピソードの自動ダウンロード",
  "LabelAutoFetchMetadata": "メタデータの自動取得",
  "LabelAutoFetchMetadataHelp": "タイトル・作者・シリーズのメタデータを取得してアップロードを効率化します。アップロード後に追加のメタデータのマッチングが必要になることがあります。",
  "LabelAutoLaunch": "自動起動",
  "LabelAutoLaunchDescription": "ログインページにアクセスすると自動的に認証プロバイダーにリダイレクトします(手動上書きパス <code>/login?autoLaunch=0</code>)",
  "LabelAutoRegister": "自動登録",
  "LabelAutoRegisterDescription": "ログイン後に新しいユーザーを自動的に作成",
  "LabelBackToUser": "ユーザーに戻る",
  "LabelBackupAudioFiles": "オーディオファイルをバックアップ",
  "LabelBackupLocation": "バックアップ場所",
  "LabelBackupsEnableAutomaticBackups": "自動バックアップ",
  "LabelBackupsEnableAutomaticBackupsHelp": "/metadata/backups に保存されたバックアップ",
  "LabelBackupsMaxBackupSize": "最大バックアップサイズ(GB)(無制限は0)",
  "LabelBackupsMaxBackupSizeHelp": "設定ミスを防ぐため、バックアップが設定サイズを超えると失敗します。",
  "LabelBackupsNumberToKeep": "保持するバックアップ数",
  "LabelBackupsNumberToKeepHelp": "一度に1つのバックアップのみ削除されます。すでにこれより多くのバックアップがある場合は手動で削除してください。",
  "LabelBitrate": "ビットレート",
  "LabelBonus": "ボーナス",
  "LabelBooks": "本",
  "LabelButtonText": "ボタンテキスト",
  "LabelByAuthor": "by {0}",
  "LabelChangePassword": "パスワードを変更",
  "LabelChannels": "チャンネル",
  "LabelChapterCount": "{0}チャプター",
  "LabelChapterTitle": "チャプタータイトル",
  "LabelChapters": "チャプター",
  "LabelChaptersFound": "チャプターが見つかりました",
  "LabelClickForMoreInfo": "クリックして詳細を表示",
  "LabelClickToUseCurrentValue": "クリックして現在の値を使用",
  "LabelClosePlayer": "プレーヤーを閉じる",
  "LabelCodec": "コーデック",
  "LabelCollapseSeries": "シリーズを折りたたむ",
  "LabelCollapseSubSeries": "サブシリーズを折りたたむ",
  "LabelCollection": "コレクション",
  "LabelCollections": "コレクション",
  "LabelComplete": "完了",
  "LabelConfirmPassword": "パスワード確認",
  "LabelContinueListening": "続きから聴く",
  "LabelContinueReading": "続きを読む",
  "LabelContinueSeries": "シリーズを続ける",
  "LabelCorsAllowed": "許可されたCORSオリジン",
  "LabelCover": "カバー",
  "LabelCoverImageURL": "カバー画像URL",
  "LabelCoverProvider": "カバープロバイダー",
  "LabelCreatedAt": "作成日時",
  "LabelCronExpression": "Cron式",
  "LabelCurrent": "現在",
  "LabelCurrently": "現在:",
  "LabelCustomCronExpression": "カスタムCron式:",
  "LabelDatetime": "日時",
  "LabelDays": "日",
  "LabelDeleteFromFileSystemCheckbox": "ファイルシステムから削除(チェック解除するとデータベースからのみ削除)",
  "LabelDescription": "説明",
  "LabelDeselectAll": "すべて解除",
  "LabelDetectedPattern": "検出されたパターン:",
  "LabelDevice": "デバイス",
  "LabelDeviceInfo": "デバイス情報",
  "LabelDeviceIsAvailableTo": "デバイスが使用可能な対象...",
  "LabelDirectory": "ディレクトリ",
  "LabelDiscFromFilename": "ファイル名からディスク",
  "LabelDiscFromMetadata": "メタデータからディスク",
  "LabelDiscover": "おすすめ",
  "LabelDownload": "ダウンロード",
  "LabelDownloadNEpisodes": "{0}エピソードをダウンロード",
  "LabelDownloadable": "ダウンロード可能",
  "LabelDuration": "長さ",
  "LabelDurationComparisonExactMatch": "(完全一致)",
  "LabelDurationComparisonLonger": "({0} 長い)",
  "LabelDurationComparisonShorter": "({0} 短い)",
  "LabelDurationFound": "見つかった長さ:",
  "LabelEbook": "電子書籍",
  "LabelEbooks": "電子書籍",
  "LabelEdit": "編集",
  "LabelEmail": "メール",
  "LabelEmailSettingsFromAddress": "送信元アドレス",
  "LabelEmailSettingsRejectUnauthorized": "未認証の証明書を拒否",
  "LabelEmailSettingsRejectUnauthorizedHelp": "SSL証明書の検証を無効にすると、中間者攻撃などのセキュリティリスクにさらされる可能性があります。接続するメールサーバーを信頼している場合にのみ無効にしてください。",
  "LabelEmailSettingsSecure": "セキュア",
  "LabelEmailSettingsSecureHelp": "trueの場合、サーバーへの接続にTLSを使用します。falseの場合、サーバーがSTARTTLS拡張をサポートしていればTLSが使用されます。ポート465に接続する場合はtrueに設定してください。ポート587または25の場合はfalseのままにしてください。(nodemailer.com/smtp/#authentication より)",
  "LabelEmailSettingsTestAddress": "テストアドレス",
  "LabelEmbeddedCover": "埋め込みカバー",
  "LabelEnable": "有効",
  "LabelEncodingBackupLocation": "元のオーディオファイルのバックアップは以下に保存されます:",
  "LabelEncodingChaptersNotEmbedded": "マルチトラックのオーディオブックにはチャプターが埋め込まれません。",
  "LabelEncodingClearItemCache": "定期的にアイテムキャッシュを削除してください。",
  "LabelEncodingFinishedM4B": "完成したM4Bはオーディオブックフォルダーに配置されます:",
  "LabelEncodingInfoEmbedded": "メタデータはオーディオブックフォルダー内のオーディオトラックに埋め込まれます。",
  "LabelEncodingStartedNavigation": "タスクが開始されたら、このページから離れることができます。",
  "LabelEncodingTimeWarning": "エンコードには最大30分かかる場合があります。",
  "LabelEncodingWarningAdvancedSettings": "警告: ffmpegエンコードオプションに詳しくない場合はこれらの設定を変更しないでください。",
  "LabelEncodingWatcherDisabled": "ウォッチャーを無効にしている場合は、後でこのオーディオブックを再スキャンする必要があります。",
  "LabelEnd": "終了",
  "LabelEndOfChapter": "チャプターの最後",
  "LabelEpisode": "エピソード",
  "LabelEpisodeNotLinkedToRssFeed": "RSSフィードにリンクされていないエピソード",
  "LabelEpisodeNumber": "エピソード#{0}",
  "LabelEpisodeTitle": "エピソードタイトル",
  "LabelEpisodeType": "エピソードタイプ",
  "LabelEpisodeUrlFromRssFeed": "RSSフィードのエピソードURL",
  "LabelEpisodes": "エピソード",
  "LabelEpisodic": "エピソード",
  "LabelExample": "例",
  "LabelExpandSeries": "シリーズを展開",
  "LabelExpandSubSeries": "サブシリーズを展開",
  "LabelExpired": "期限切れ",
  "LabelExpiresAt": "有効期限",
  "LabelExpiresInSeconds": "有効期限(秒)",
  "LabelExpiresNever": "なし",
  "LabelExplicit": "露骨な表現",
  "LabelExplicitChecked": "露骨な表現あり(チェック済み)",
  "LabelExplicitUnchecked": "露骨な表現なし(未チェック)",
  "LabelExportOPML": "OPMLをエクスポート",
  "LabelFeedURL": "フィードURL",
  "LabelFetchingMetadata": "メタデータ取得中",
  "LabelFile": "ファイル",
  "LabelFileBirthtime": "ファイル作成日時",
  "LabelFileBornDate": "{0}に生成",
  "LabelFileModified": "ファイル更新日時",
  "LabelFileModifiedDate": "{0}に更新",
  "LabelFilename": "ファイル名",
  "LabelFilterByUser": "ユーザーでフィルター",
  "LabelFindEpisodes": "エピソードを検索",
  "LabelFinished": "完了",
  "LabelFinishedDate": "{0}に完了",
  "LabelFolder": "フォルダー",
  "LabelFolders": "フォルダー",
  "LabelFontBold": "太字",
  "LabelFontBoldness": "フォントの太さ",
  "LabelFontFamily": "フォントファミリー",
  "LabelFontItalic": "斜体",
  "LabelFontScale": "フォントサイズ",
  "LabelFontStrikethrough": "打消線",
  "LabelFormat": "形式",
  "LabelFull": "完全",
  "LabelGenre": "ジャンル",
  "LabelGenres": "ジャンル",
  "LabelHardDeleteFile": "ファイルを完全削除",
  "LabelHasEbook": "電子書籍あり",
  "LabelHasSupplementaryEbook": "付属電子書籍あり",
  "LabelHideSubtitles": "字幕を非表示",
  "LabelHighestPriority": "最高優先度",
  "LabelHost": "ホスト",
  "LabelHour": "時間",
  "LabelHours": "時間",
  "LabelIcon": "アイコン",
  "LabelImageURLFromTheWeb": "ウェブからの画像URL",
  "LabelInProgress": "進行中",
  "LabelIncludeInTracklist": "トラックリストに含める",
  "LabelIncomplete": "未完了",
  "LabelInterval": "間隔",
  "LabelIntervalCustomDailyWeekly": "カスタム(毎日/曜日指定)",
  "LabelIntervalEvery12Hours": "12時間ごと",
  "LabelIntervalEvery15Minutes": "15分ごと",
  "LabelIntervalEvery2Hours": "2時間ごと",
  "LabelIntervalEvery30Minutes": "30分ごと",
  "LabelIntervalEvery6Hours": "6時間ごと",
  "LabelIntervalEveryDay": "毎日",
  "LabelIntervalEveryHour": "1時間ごと",
  "LabelIntervalEveryMinute": "1分ごと",
  "LabelInvert": "反転",
  "LabelItem": "アイテム",
  "LabelJumpBackwardAmount": "巻き戻し量",
  "LabelJumpForwardAmount": "早送り量",
  "LabelLanguage": "言語",
  "LabelLanguageDefaultServer": "デフォルトサーバー言語",
  "LabelLanguages": "言語",
  "LabelLastBookAdded": "最後に追加された本",
  "LabelLastBookUpdated": "最後に更新された本",
  "LabelLastProgressDate": "最終進捗: {0}",
  "LabelLastSeen": "最終確認",
  "LabelLastTime": "終了時刻",
  "LabelLastUpdate": "最終更新",
  "LabelLayout": "レイアウト",
  "LabelLayoutSinglePage": "単ページ",
  "LabelLayoutSplitPage": "ページを分割",
  "LabelLess": "少ない",
  "LabelLibrariesAccessibleToUser": "ユーザーがアクセス可能なライブラリー",
  "LabelLibrary": "ライブラリー",
  "LabelLibraryFilterSublistEmpty": "{0}がない",
  "LabelLibraryItem": "ライブラリーアイテム",
  "LabelLibraryName": "ライブラリー名",
  "LabelLibrarySortByProgress": "進捗: 最終更新",
  "LabelLibrarySortByProgressFinished": "進捗: 完了",
  "LabelLibrarySortByProgressStarted": "進捗: 開始済み",
  "LabelLimit": "制限",
  "LabelLineSpacing": "行間",
  "LabelListenAgain": "もう一度聴く",
  "LabelLogLevelDebug": "デバッグ",
  "LabelLogLevelInfo": "情報",
  "LabelLogLevelWarn": "警告",
  "LabelLookForNewEpisodesAfterDate": "この日以降の新しいエピソードを検索",
  "LabelLowestPriority": "最低優先度",
  "LabelMatchConfidence": "信頼度",
  "LabelMatchExistingUsersBy": "既存ユーザーの照合方法",
  "LabelMatchExistingUsersByDescription": "既存ユーザーの接続に使用されます。接続後はSSOプロバイダーの一意のIDでユーザーが照合されます",
  "LabelMaxEpisodesToDownload": "最大ダウンロードエピソード数(無制限は0)。",
  "LabelMaxEpisodesToDownloadPerCheck": "1回のチェックでダウンロードする最大の新着エピソード数",
  "LabelMaxEpisodesToKeep": "保持する最大エピソード数",
  "LabelMaxEpisodesToKeepHelp": "0は上限なし。新しいエピソードの自動ダウンロード後、X件以上のエピソードがある場合は最も古いエピソードを削除します。1回のダウンロードにつき1件のみ削除されます。",
  "LabelMediaPlayer": "メディアプレーヤー",
  "LabelMediaType": "メディアの種類",
  "LabelMetaTag": "メタタグ",
  "LabelMetaTags": "メタタグ",
  "LabelMetadataOrderOfPrecedenceDescription": "優先度の高いメタデータソースが優先度の低いメタデータソースを上書きします",
  "LabelMetadataProvider": "メタデータプロバイダー",
  "LabelMinute": "分",
  "LabelMinutes": "分",
  "LabelMissing": "消失",
  "LabelMissingEbook": "電子書籍なし",
  "LabelMissingSupplementaryEbook": "付属電子書籍なし",
  "LabelMobileRedirectURIs": "許可されたモバイルリダイレクトURI",
  "LabelMobileRedirectURIsDescription": "これはモバイルアプリの有効なリダイレクトURIのホワイトリストです。デフォルトは <code>audiobookshelf://oauth</code> です。削除するか、サードパーティーアプリ統合用の追加URIで補足できます。アスタリスク(<code>*</code>)を唯一のエントリとして使用すると、任意のURIが許可されます。",
  "LabelMore": "多い",
  "LabelMoreInfo": "追加情報",
  "LabelName": "名前",
  "LabelNarrator": "ナレーター",
  "LabelNarrators": "ナレーター",
  "LabelNew": "新しい",
  "LabelNewPassword": "新しいパスワード",
  "LabelNewestAuthors": "最新の作者",
  "LabelNewestEpisodes": "最新エピソード",
  "LabelNextBackupDate": "次回バックアップ日",
  "LabelNextChapters": "次のチャプター:",
  "LabelNextScheduledRun": "次のスケジュール実行",
  "LabelNoApiKeys": "APIキーなし",
  "LabelNoCustomMetadataProviders": "カスタムメタデータプロバイダーなし",
  "LabelNoEpisodesSelected": "エピソードが選択されていません",
  "LabelNotFinished": "未完了",
  "LabelNotStarted": "未開始",
  "LabelNotes": "ノート",
  "LabelNotificationAppriseURL": "Apprise URL",
  "LabelNotificationAvailableVariables": "利用可能な変数",
  "LabelNotificationBodyTemplate": "本文テンプレート",
  "LabelNotificationEvent": "通知イベント",
  "LabelNotificationTitleTemplate": "タイトルテンプレート",
  "LabelNotificationsMaxFailedAttempts": "最大失敗試行回数",
  "LabelNotificationsMaxFailedAttemptsHelp": "この回数失敗すると通知は無効になります",
  "LabelNotificationsMaxQueueSize": "通知イベントの最大キューサイズ",
  "LabelNotificationsMaxQueueSizeHelp": "イベントは1秒に1回の発火に制限されます。キューが最大サイズの場合、イベントは無視されます。これは通知スパムを防ぎます。",
  "LabelNumberOfBooks": "本の冊数",
  "LabelNumberOfChapters": "チャプター数:",
  "LabelNumberOfEpisodes": "エピソード数",
  "LabelOpenIDAdvancedPermsClaimDescription": "管理者以外のロールに適用されるアプリケーション内のユーザーアクション用の高度な権限を含むOpenIDクレーム名(<b>設定されている場合</b>)。クレームがレスポンスに含まれていない場合、ABSへのアクセスは拒否されます。単一のオプションがない場合は <code>false</code> として扱われます。IDプロバイダーのクレームが期待される構造と一致することを確認してください:",
  "LabelOpenIDClaims": "以下のオプションを空のままにすると、高度なグループと権限の割り当てが無効になり、自動的に「User」グループが割り当てられます。",
  "LabelOpenIDGroupClaimDescription": "ユーザーのグループリストを含むOpenIDクレーム名。一般的には <code>groups</code> と呼ばれます。<b>設定されている場合</b>、アプリケーションはユーザーのグループメンバーシップに基づいて自動的にロールを割り当てます。クレームのグループ名が大文字小文字を区別せずに「admin」「user」「guest」である場合、対応するロールが割り当てられます。グループが一致しない場合、アクセスは拒否されます。",
  "LabelOpenRSSFeed": "RSSフィードを開く",
  "LabelOverwrite": "上書き",
  "LabelPaginationPageXOfY": "{0}/{1}ページ",
  "LabelPassword": "パスワード",
  "LabelPath": "パス",
  "LabelPermanent": "無期限",
  "LabelPermissionsAccessAllLibraries": "すべてのライブラリーにアクセス可能",
  "LabelPermissionsAccessAllTags": "すべてのタグにアクセス可能",
  "LabelPermissionsAccessExplicitContent": "露骨なコンテンツにアクセス可能",
  "LabelPermissionsCreateEreader": "電子書籍リーダー作成可能",
  "LabelPermissionsDelete": "削除可能",
  "LabelPermissionsDownload": "ダウンロード可能",
  "LabelPermissionsUpdate": "更新可能",
  "LabelPermissionsUpload": "アップロード可能",
  "LabelPersonalYearReview": "個人の年間振り返り({0})",
  "LabelPhotoPathURL": "写真パス/URL",
  "LabelPlayMethod": "再生方法",
  "LabelPlaybackRateIncrementDecrement": "再生速度の増減量",
  "LabelPlayerChapterNumberMarker": "{0}/{1}",
  "LabelPlaylists": "プレイリスト",
  "LabelPodcast": "ポッドキャスト",
  "LabelPodcastSearchRegion": "ポッドキャスト検索地域",
  "LabelPodcastType": "ポッドキャストタイプ",
  "LabelPodcasts": "ポッドキャスト",
  "LabelPort": "ポート",
  "LabelPrefixesToIgnore": "無視するプレフィックス(大文字小文字を区別しない)",
  "LabelPreventIndexing": "フィードがiTunesおよびGoogleのポッドキャストディレクトリにインデックス登録されるのを防ぎます",
  "LabelPrimaryEbook": "メイン電子書籍",
  "LabelProgress": "進捗",
  "LabelProvider": "プロバイダー",
  "LabelProviderAuthorizationValue": "認証ヘッダーの値",
  "LabelPubDate": "公開日",
  "LabelPublishYear": "公開年",
  "LabelPublishedDate": "{0}発行",
  "LabelPublishedDecade": "発行年代",
  "LabelPublishedDecades": "発行年代",
  "LabelPublisher": "出版社",
  "LabelPublishers": "出版社",
  "LabelRSSFeedCustomOwnerEmail": "カスタムオーナーメール",
  "LabelRSSFeedCustomOwnerName": "カスタムオーナー名",
  "LabelRSSFeedOpen": "RSSフィードを公開",
  "LabelRSSFeedPreventIndexing": "インデックス化を防止",
  "LabelRSSFeedSlug": "RSSフィードスラグ",
  "LabelRSSFeedURL": "RSSフィードURL",
  "LabelRandomly": "ランダム",
  "LabelReAddSeriesToContinueListening": "シリーズを再追加して「続きを聴く」に戻す",
  "LabelRead": "読む",
  "LabelReadAgain": "もう一度読む",
  "LabelReadEbookWithoutProgress": "進捗を記録せずに電子書籍を読む",
  "LabelRecentSeries": "最近のシリーズ",
  "LabelRecentlyAdded": "最近追加",
  "LabelRecommended": "おすすめ",
  "LabelRedo": "やり直す",
  "LabelRegion": "地域",
  "LabelReleaseDate": "リリース日",
  "LabelRemoveAllMetadataAbs": "すべてのmetadata.absファイルを削除",
  "LabelRemoveAllMetadataJson": "すべてのmetadata.jsonファイルを削除",
  "LabelRemoveAudibleBranding": "Audibleのイントロとアウトロをチャプターから削除",
  "LabelRemoveCover": "カバーを削除",
  "LabelRemoveMetadataFile": "ライブラリーアイテムフォルダー内のメタデータファイルを削除",
  "LabelRemoveMetadataFileHelp": "{0}フォルダー内のすべてのmetadata.jsonおよびmetadata.absファイルを削除します。",
  "LabelRowsPerPage": "1ページあたりの行数",
  "LabelSearchTerm": "検索ワード",
  "LabelSearchTitle": "タイトルを検索",
  "LabelSearchTitleOrASIN": "タイトルまたはASINを検索",
  "LabelSeason": "シーズン",
  "LabelSeasonNumber": "シーズン#{0}",
  "LabelSelectAll": "すべて選択",
  "LabelSelectAllEpisodes": "すべてのエピソードを選択",
  "LabelSelectEpisodesShowing": "表示中の{0}件のエピソードを選択",
  "LabelSelectUser": "ユーザーを選択",
  "LabelSelectUsers": "ユーザーを選択",
  "LabelSendEbookToDevice": "電子書籍を送信...",
  "LabelSequence": "シーケンス",
  "LabelSerial": "シリアル",
  "LabelSeries": "シリーズ",
  "LabelSeriesName": "シリーズ名",
  "LabelSeriesProgress": "シリーズ進捗",
  "LabelServerLogLevel": "サーバーログレベル",
  "LabelServerYearReview": "サーバーの年間振り返り({0})",
  "LabelSetEbookAsPrimary": "メインとして設定",
  "LabelSetEbookAsSupplementary": "付属として設定",
  "LabelSettingsAllowIframe": "iframeへの埋め込みを許可",
  "LabelSettingsAudiobooksOnly": "オーディオブックのみ",
  "LabelSettingsAudiobooksOnlyHelp": "この設定を有効にすると電子書籍ファイルは無視されます。ただしオーディオブックフォルダー内の電子書籍は付属電子書籍として設定されます",
  "LabelSettingsBookshelfViewHelp": "木製の棚を備えたスキューモーフィックデザイン",
  "LabelSettingsChromecastSupport": "Chromecastサポート",
  "LabelSettingsDateFormat": "日付フォーマット",
  "LabelSettingsEnableWatcher": "ライブラリーの変更を自動的に監視する",
  "LabelSettingsEnableWatcherForLibrary": "ライブラリーの変更を自動的に監視する",
  "LabelSettingsEnableWatcherHelp": "ファイルの変更が検出されたときにアイテムの自動追加/更新を有効にします。*サーバーの再起動が必要です",
  "LabelSettingsEpubsAllowScriptedContent": "epubのスクリプトコンテンツを許可",
  "LabelSettingsEpubsAllowScriptedContentHelp": "epubファイルがスクリプトを実行することを許可します。epubファイルのソースを信頼しない限り、この設定を無効のままにすることをお勧めします。",
  "LabelSettingsExperimentalFeatures": "実験的機能",
  "LabelSettingsExperimentalFeaturesHelp": "開発中の機能でご意見とテストのご協力をお願いしています。クリックしてGitHubディスカッションを開く。",
  "LabelSettingsFindCovers": "表紙を探す",
  "LabelSettingsFindCoversHelp": "もしオーディオブックに表紙が埋め込まれていない、もしくは表紙画像がフォルダー内に見つからなければ、スキャナーは表紙を探そうとします。<br>注: これによってスキャン時間が長くなります",
  "LabelSettingsHideSingleBookSeries": "単一の本のシリーズを非表示",
  "LabelSettingsHideSingleBookSeriesHelp": "単一の本を持つシリーズはシリーズページとホームページの棚から非表示になります。",
  "LabelSettingsHomePageBookshelfView": "ホームページは本棚ビューを使用",
  "LabelSettingsLibraryBookshelfView": "ライブラリーは本棚ビューを使用",
  "LabelSettingsLibraryMarkAsFinishedPercentComplete": "完了率が次より大きい",
  "LabelSettingsLibraryMarkAsFinishedTimeRemaining": "残り時間が次より少ない(秒)",
  "LabelSettingsLibraryMarkAsFinishedWhen": "メディアアイテムを完了としてマークする条件",
  "LabelSettingsOnlyShowLaterBooksInContinueSeries": "「シリーズを続ける」で前の本をスキップ",
  "LabelSettingsOnlyShowLaterBooksInContinueSeriesHelp": "「シリーズを続ける」のホームページ棚は、1冊以上完了していて進行中の本がないシリーズの最初の未開始の本を表示します。この設定を有効にすると、最初の未開始の本ではなく、最後に完了した本からシリーズが継続されます。",
  "LabelSettingsParseSubtitles": "サブタイトルを抽出する",
  "LabelSettingsParseSubtitlesHelp": "オーディオブックのフォルダー名からサブタイトルを抽出します。<br>サブタイトルは \"-\" で区切ってください<br>例: \"本のタイトル - ここにサブタイトル\" という名前だと \"ここにサブタイトル\" というサブタイトルになります",
  "LabelSettingsPreferMatchedMetadata": "一致したメタデータを優先する",
  "LabelSettingsPreferMatchedMetadataHelp": "クイックマッチを使用する時、一致したデータは書籍の詳細を上書きします。デフォルトでは、埋まっていない項目のみ入力されます。",
  "LabelSettingsSkipMatchingBooksWithASIN": "ASINを持つ本のマッチングをスキップ",
  "LabelSettingsSkipMatchingBooksWithISBN": "ISBNを持つ本のマッチングをスキップ",
  "LabelSettingsSortingIgnorePrefixes": "並び替えでプレフィックスを無視する",
  "LabelSettingsSortingIgnorePrefixesHelp": "例: プレフィックス \"the\" の付いた本のタイトル \"The Book Title\" は \"Book Title, The\" として並び替えられます",
  "LabelSettingsSquareBookCovers": "正方形の本のカバーを使用",
  "LabelSettingsSquareBookCoversHelp": "標準の1.6:1のカバーより正方形のカバーを優先",
  "LabelSettingsStoreCoversWithItem": "表紙を項目と一緒に保存する",
  "LabelSettingsStoreCoversWithItemHelp": "デフォルトでは表紙は /metadata/items に保存されますが、この設定をオンにするとライブラリーの項目のフォルダーに保存されます。\"cover\" という名前のファイル一つのみが保持されます",
  "LabelSettingsStoreMetadataWithItem": "メタデータを項目と一緒に保存する",
  "LabelSettingsStoreMetadataWithItemHelp": "デフォルトではメタデータは/metadata/itemsに保存されますが、この設定をオンにするとライブラリーの項目のフォルダーに保存されます",
  "LabelSettingsTimeFormat": "時刻フォーマット",
  "LabelShare": "共有",
  "LabelShareDownloadableHelp": "共有リンクを持つユーザーがライブラリーアイテムのzipファイルをダウンロードできるようにします。",
  "LabelShareOpen": "共有を公開",
  "LabelShareURL": "共有URL",
  "LabelShowAll": "すべて表示",
  "LabelShowSeconds": "秒を表示",
  "LabelShowSubtitles": "字幕を表示",
  "LabelSize": "サイズ",
  "LabelSleepTimer": "スリープタイマー",
  "LabelSlug": "スラグ",
  "LabelSortAscending": "昇順",
  "LabelSortDescending": "降順",
  "LabelSortPubDate": "公開日でソート",
  "LabelStart": "開始",
  "LabelStartTime": "開始時刻",
  "LabelStarted": "開始済み",
  "LabelStartedAt": "開始日時",
  "LabelStartedDate": "{0}に開始",
  "LabelStatsAudioTracks": "オーディオトラック",
  "LabelStatsAuthors": "作者",
  "LabelStatsBestDay": "日ごとの最長",
  "LabelStatsDailyAverage": "日ごとの平均",
  "LabelStatsDays": "日数",
  "LabelStatsDaysListened": "聴いた日数",
  "LabelStatsHours": "時間",
  "LabelStatsInARow": "連続",
  "LabelStatsItemsFinished": "完了したアイテム",
  "LabelStatsItemsInLibrary": "ライブラリー内のアイテム",
  "LabelStatsMinutes": "分",
  "LabelStatsMinutesListening": "聴いた時間(分)",
  "LabelStatsOverallDays": "総日数",
  "LabelStatsOverallHours": "総時間",
  "LabelStatsWeekListening": "週間リスニング",
  "LabelSubtitle": "サブタイトル",
  "LabelSupportedFileTypes": "サポートされているファイルタイプ",
  "LabelTag": "タグ",
  "LabelTags": "タグ",
  "LabelTagsAccessibleToUser": "ユーザーがアクセス可能なタグ",
  "LabelTagsNotAccessibleToUser": "ユーザーがアクセスできないタグ",
  "LabelTasks": "実行中のタスク",
  "LabelTextEditorBulletedList": "箇条書きリスト",
  "LabelTextEditorLink": "リンク",
  "LabelTextEditorNumberedList": "番号付きリスト",
  "LabelTextEditorUnlink": "リンク解除",
  "LabelTheme": "テーマ",
  "LabelThemeDark": "ダーク",
  "LabelThemeLight": "ライト",
  "LabelThemeSepia": "セピア",
  "LabelTimeBase": "タイムベース",
  "LabelTimeDurationXHours": "{0}時間",
  "LabelTimeDurationXMinutes": "{0}分",
  "LabelTimeDurationXSeconds": "{0}秒",
  "LabelTimeInMinutes": "時間(分単位)",
  "LabelTimeLeft": "残り{0}",
  "LabelTimeListened": "リスニング時間",
  "LabelTimeListenedToday": "本日のリスニング時間",
  "LabelTimeRemaining": "残り{0}",
  "LabelTimeToShift": "シフトする時間(秒単位)",
  "LabelTitle": "タイトル",
  "LabelToolsEmbedMetadata": "メタデータの埋め込み",
  "LabelToolsEmbedMetadataDescription": "カバー画像とチャプターを含むメタデータをオーディオファイルに埋め込みます。",
  "LabelToolsM4bEncoder": "M4Bエンコーダー",
  "LabelToolsMakeM4b": "M4Bオーディオブックファイルを作成",
  "LabelToolsMakeM4bDescription": "メタデータ、カバー画像、チャプターを埋め込んだ.M4Bオーディオブックファイルを生成します。",
  "LabelToolsSplitM4b": "M4BをMP3に分割",
  "LabelToolsSplitM4bDescription": "メタデータ、カバー画像、チャプターを埋め込んだチャプター分割MP3ファイルをM4Bから作成します。",
  "LabelTotalDuration": "総再生時間",
  "LabelTotalTimeListened": "合計リスニング時間",
  "LabelTrackFromFilename": "ファイル名からトラック",
  "LabelTrackFromMetadata": "メタデータからトラック",
  "LabelTracks": "トラック",
  "LabelTracksMultiTrack": "マルチトラック",
  "LabelTracksNone": "トラックなし",
  "LabelTracksSingleTrack": "シングルトラック",
  "LabelTrailer": "トレーラー",
  "LabelType": "タイプ",
  "LabelUnabridged": "完全版",
  "LabelUndo": "元に戻す",
  "LabelUnknown": "不明",
  "LabelUnknownPublishDate": "公開日不明",
  "LabelUpdateCover": "カバーを更新",
  "LabelUpdateCoverHelp": "マッチが見つかった場合、選択した本の既存のカバーの上書きを許可",
  "LabelUpdateDetails": "詳細を更新",
  "LabelUpdateDetailsHelp": "マッチが見つかった場合、選択した本の既存の詳細の上書きを許可",
  "LabelUpdatedAt": "更新日時",
  "LabelUploaderDragAndDrop": "ファイルまたはフォルダーをドラッグ&ドロップ",
  "LabelUploaderDragAndDropFilesOnly": "ファイルをドラッグ&ドロップ",
  "LabelUploaderDropFiles": "ファイルをドロップ",
  "LabelUploaderItemFetchMetadataHelp": "タイトル、作者、シリーズを自動取得",
  "LabelUseAdvancedOptions": "詳細オプションを使用",
  "LabelUseChapterTrack": "チャプタートラックを使用",
  "LabelUseFullTrack": "フルトラックを使用",
  "LabelUseZeroForUnlimited": "0で無制限",
  "LabelUser": "ユーザー",
  "LabelUsername": "ユーザー名",
  "LabelValue": "値",
  "LabelVersion": "バージョン",
  "LabelViewBookmarks": "ブックマークを表示",
  "LabelViewChapters": "チャプターを表示",
  "LabelViewPlayerSettings": "プレーヤー設定を表示",
  "LabelViewQueue": "「次に再生」を表示",
  "LabelVolume": "ボリューム",
  "LabelWebRedirectURLsDescription": "ログイン後にウェブアプリへのリダイレクトを許可するため、OAuthプロバイダーでこれらのURLを認可してください:",
  "LabelWebRedirectURLsSubfolder": "リダイレクトURLのサブフォルダー",
  "LabelWeekdaysToRun": "実行する曜日",
  "LabelXBooks": "{0}冊の本",
  "LabelXItems": "{0}件のアイテム",
  "LabelYearReviewHide": "年間振り返りを非表示",
  "LabelYearReviewShow": "年間振り返りを表示",
  "LabelYourAudiobookDuration": "オーディオブックの再生時間",
  "LabelYourBookmarks": "ブックマーク",
  "LabelYourPlaylists": "プレイリスト",
  "LabelYourProgress": "進捗状況",
  "MessageAddToPlayerQueue": "「次に再生」に追加",
  "MessageAppriseDescription": "この機能を使用するには、<a href=\"https://github.com/caronc/apprise-api\" target=\"_blank\">Apprise API</a> のインスタンスを起動するか、同じリクエストを処理できるAPIが必要です。<br />Apprise API URLは通知を送信するための完全なURLパスである必要があります。例えば、APIインスタンスが <code>http://192.168.1.1:8337</code> で起動している場合は <code>http://192.168.1.1:8337/notify</code> を入力してください。",
  "MessageAsinCheck": "AmazonではなくAudibleの正しいリージョンのASINを使用していることを確認してください。",
  "MessageAuthenticationLegacyTokenWarning": "レガシーAPIトークンは将来削除されます。代わりに <a href=\"/config/api-keys\">APIキー</a> を使用してください。",
  "MessageAuthenticationOIDCChangesRestart": "OIDCの変更を適用するには、保存後にサーバーを再起動してください。",
  "MessageAuthenticationSecurityMessage": "セキュリティのため認証が改善されました。すべてのユーザーは再ログインが必要です。",
  "MessageBackupsDescription": "バックアップにはユーザー、ユーザーの進捗状況、ライブラリーアイテムの詳細、サーバー設定、および <code>/metadata/items</code> と <code>/metadata/authors</code> に保存されている画像が含まれます。バックアップにはライブラリーフォルダーに保存されているファイルは<strong>含まれません</strong>。",
  "MessageBackupsLocationEditNote": "注: バックアップ場所を更新しても、既存のバックアップは移動または変更されません",
  "MessageBackupsLocationNoEditNote": "注: バックアップ場所は環境変数で設定されており、ここでは変更できません。",
  "MessageBackupsLocationPathEmpty": "バックアップ場所のパスは空にできません",
  "MessageBatchEditPopulateMapDetailsAllHelp": "すべてのアイテムのデータで有効なフィールドを設定します。複数の値があるフィールドはマージされます",
  "MessageBatchEditPopulateMapDetailsItemHelp": "このアイテムのデータで有効なマップ詳細フィールドを設定します",
  "MessageBatchQuickMatchDescription": "クイックマッチは選択したアイテムの不足しているカバーとメタデータを追加しようとします。クイックマッチが既存のカバーやメタデータを上書きできるようにするには、以下のオプションを有効にしてください。",
  "MessageBookshelfNoCollections": "まだコレクションを作成していません",
  "MessageBookshelfNoCollectionsHelp": "コレクションは公開されています。ライブラリーにアクセスできるすべてのユーザーが見ることができます。",
  "MessageBookshelfNoRSSFeeds": "公開中のRSSフィードはありません",
  "MessageBookshelfNoResultsForFilter": "フィルター \"{0}: {1}\" に一致する結果がありません",
  "MessageBookshelfNoResultsForQuery": "クエリに一致する結果がありません",
  "MessageBookshelfNoSeries": "シリーズがありません",
  "MessageBulkChapterPattern": "この番号パターンでいくつのチャプターを追加しますか？",
  "MessageChapterEndIsAfter": "チャプターの終了がオーディオブックの末尾を超えています",
  "MessageChapterErrorFirstNotZero": "最初のチャプターは0から始まる必要があります",
  "MessageChapterErrorStartGteDuration": "開始時間はオーディオブックの長さより短くなければなりません",
  "MessageChapterErrorStartLtPrev": "開始時間は前のチャプターの開始時間以上でなければなりません",
  "MessageChapterStartIsAfter": "チャプターの開始がオーディオブックの末尾を超えています",
  "MessageChaptersNotFound": "チャプターが見つかりません",
  "MessageCheckingCron": "cronを確認中...",
  "MessageConfirmCloseFeed": "このフィードを閉じてもよろしいですか？",
  "MessageConfirmDeleteApiKey": "APIキー \"{0}\" を削除してもよろしいですか？",
  "MessageConfirmDeleteBackup": "{0} のバックアップを削除してもよろしいですか？",
  "MessageConfirmDeleteDevice": "電子書籍リーダー端末 \"{0}\" を削除してもよろしいですか？",
  "MessageConfirmDeleteFile": "ファイルシステムからファイルを削除します。よろしいですか？",
  "MessageConfirmDeleteLibrary": "ライブラリー \"{0}\" を完全に削除してもよろしいですか？",
  "MessageConfirmDeleteLibraryItem": "データベースとファイルシステムからライブラリーアイテムを削除します。よろしいですか？",
  "MessageConfirmDeleteLibraryItems": "データベースとファイルシステムから {0}件のライブラリーアイテムを削除します。よろしいですか？",
  "MessageConfirmDeleteMetadataProvider": "カスタムメタデータプロバイダー \"{0}\" を削除してもよろしいですか？",
  "MessageConfirmDeleteNotification": "この通知を削除してもよろしいですか？",
  "MessageConfirmDeleteSession": "このセッションを削除してもよろしいですか？",
  "MessageConfirmEmbedMetadataInAudioFiles": "{0}件のオーディオファイルにメタデータを埋め込んでもよろしいですか？",
  "MessageConfirmForceReScan": "強制的に再スキャンしてもよろしいですか？",
  "MessageConfirmMarkAllEpisodesFinished": "すべてのエピソードを完了済みにしてもよろしいですか？",
  "MessageConfirmMarkAllEpisodesNotFinished": "すべてのエピソードを未完了にしてもよろしいですか？",
  "MessageConfirmMarkItemFinished": "\"{0}\" を完了済みにしてもよろしいですか？",
  "MessageConfirmMarkItemNotFinished": "\"{0}\" を未完了にしてもよろしいですか？",
  "MessageConfirmMarkSeriesFinished": "このシリーズのすべての本を完了済みにしてもよろしいですか？",
  "MessageConfirmMarkSeriesNotFinished": "このシリーズのすべての本を未完了にしてもよろしいですか？",
  "MessageConfirmNotificationTestTrigger": "テストデータでこの通知をトリガーしてもよろしいですか？",
  "MessageConfirmPurgeCache": "キャッシュの削除により <code>/metadata/cache</code> ディレクトリ全体が削除されます。<br /><br />キャッシュディレクトリを削除してもよろしいですか？",
  "MessageConfirmPurgeItemsCache": "アイテムキャッシュの削除により <code>/metadata/cache/items</code> ディレクトリ全体が削除されます。<br />よろしいですか？",
  "MessageConfirmQuickEmbed": "警告！クイック埋め込みはオーディオファイルをバックアップしません。オーディオファイルのバックアップがあることを確認してください。<br><br>続行しますか？",
  "MessageConfirmQuickMatchEpisodes": "エピソードのクイックマッチは一致が見つかった場合に詳細を上書きします。未マッチのエピソードのみ更新されます。よろしいですか？",
  "MessageConfirmReScanLibraryItems": "{0}件のアイテムを再スキャンしてもよろしいですか？",
  "MessageConfirmRemoveAllChapters": "すべてのチャプターを削除してもよろしいですか？",
  "MessageConfirmRemoveAuthor": "作者 \"{0}\" を削除してもよろしいですか？",
  "MessageConfirmRemoveCollection": "コレクション \"{0}\" を削除してもよろしいですか？",
  "MessageConfirmRemoveEpisode": "エピソード \"{0}\" を削除してもよろしいですか？",
  "MessageConfirmRemoveEpisodeNote": "注: 「ファイルも削除する」を有効にしない限り、オーディオファイルは削除されません",
  "MessageConfirmRemoveEpisodes": "{0}件のエピソードを削除してもよろしいですか？",
  "MessageConfirmRemoveListeningSessions": "{0}件のリスニングセッションを削除してもよろしいですか？",
  "MessageConfirmRemoveMetadataFiles": "ライブラリーアイテムフォルダー内のすべての metadata.{0} ファイルを削除してもよろしいですか？",
  "MessageConfirmRemoveNarrator": "ナレーター \"{0}\" を削除してもよろしいですか？",
  "MessageConfirmRemovePlaylist": "プレイリスト \"{0}\" を削除してもよろしいですか？",
  "MessageConfirmRenameGenre": "すべてのアイテムのジャンル \"{0}\" を \"{1}\" に変更してもよろしいですか？",
  "MessageConfirmRenameGenreMergeNote": "注: このジャンルはすでに存在するためマージされます。",
  "MessageConfirmRenameGenreWarning": "警告！大文字・小文字が異なる類似したジャンル \"{0}\" がすでに存在します。",
  "MessageConfirmRenameTag": "すべてのアイテムのタグ \"{0}\" を \"{1}\" に変更してもよろしいですか？",
  "MessageConfirmRenameTagMergeNote": "注: このタグはすでに存在するためマージされます。",
  "MessageConfirmRenameTagWarning": "警告！大文字・小文字が異なる類似したタグ \"{0}\" がすでに存在します。",
  "MessageConfirmResetProgress": "進捗状況をリセットしてもよろしいですか？",
  "MessageConfirmSendEbookToDevice": "{0} の電子書籍 \"{1}\" を端末 \"{2}\" に送信してもよろしいですか？",
  "MessageConfirmUnlinkOpenId": "このユーザーをOpenIDからリンク解除してもよろしいですか？",
  "MessageDaysListenedInTheLastYear": "過去1年間に {0}日間聴きました",
  "MessageDownloadingEpisode": "エピソードをダウンロード中",
  "MessageDragFilesIntoTrackOrder": "ファイルを正しいトラック順にドラッグしてください",
  "MessageEmbedFailed": "埋め込み失敗！",
  "MessageEmbedFinished": "埋め込み完了！",
  "MessageEmbedQueue": "メタデータ埋め込みキューに追加されました(キュー内: {0}件)",
  "MessageEpisodesQueuedForDownload": "{0}件のエピソードがダウンロードキューに追加されました",
  "MessageEreaderDevices": "電子書籍を確実に配信するため、以下の各端末で上記のメールアドレスを送信元として許可する設定が必要になることがあります。",
  "MessageFeedURLWillBe": "フィードURLは {0} になります",
  "MessageFetching": "取得中...",
  "MessageForceReScanDescription": "すべてのファイルを新規スキャンのように再スキャンします。オーディオファイルのID3タグ、OPFファイル、テキストファイルが新規として読み込まれます。",
  "MessageHeatmapListeningTimeTooltip": "{1} に <strong>{0} のリスニング</strong>",
  "MessageHeatmapNoListeningSessions": "{0} にリスニングセッションはありません",
  "MessageImportantNotice": "重要なお知らせ！",
  "MessageInsertChapterBelow": "下にチャプターを挿入",
  "MessageInvalidAsin": "無効なASIN",
  "MessageItemsSelected": "{0}件選択中",
  "MessageItemsUpdated": "{0}件更新されました",
  "MessageJoinUsOn": "参加する:",
  "MessageLoading": "読み込み中...",
  "MessageLoadingFolders": "フォルダーを読み込み中...",
  "MessageLogsDescription": "ログは <code>/metadata/logs</code> にJSONファイルとして保存されます。クラッシュログは <code>/metadata/logs/crash_logs.txt</code> に保存されます。",
  "MessageM4BFailed": "M4B変換失敗！",
  "MessageM4BFinished": "M4B変換完了！",
  "MessageMapChapterTitles": "タイムスタンプを調整せずにチャプタータイトルを既存のオーディオブックのチャプターに割り当てます",
  "MessageMarkAllEpisodesFinished": "すべてのエピソードを完了済みにする",
  "MessageMarkAllEpisodesNotFinished": "すべてのエピソードを未完了にする",
  "MessageMarkAsFinished": "完了済みにする",
  "MessageMarkAsNotFinished": "未完了にする",
  "MessageMatchBooksDescription": "ライブラリー内の本を選択した検索プロバイダーの本と照合し、空の詳細とカバーアートを補完しようとします。既存の詳細は上書きしません。",
  "MessageNoAudioTracks": "オーディオトラックなし",
  "MessageNoAuthors": "作者なし",
  "MessageNoBackups": "バックアップなし",
  "MessageNoBookmarks": "ブックマークなし",
  "MessageNoChapters": "チャプターなし",
  "MessageNoCollections": "コレクションなし",
  "MessageNoCoversFound": "カバーが見つかりません",
  "MessageNoDescription": "説明なし",
  "MessageNoDevices": "端末なし",
  "MessageNoDownloadsInProgress": "現在進行中のダウンロードはありません",
  "MessageNoDownloadsQueued": "ダウンロードキューが空です",
  "MessageNoEpisodeMatchesFound": "エピソードの一致が見つかりません",
  "MessageNoEpisodes": "エピソードなし",
  "MessageNoFoldersAvailable": "利用可能なフォルダーがありません",
  "MessageNoGenres": "ジャンルなし",
  "MessageNoIssues": "問題なし",
  "MessageNoItems": "アイテムなし",
  "MessageNoItemsFound": "アイテムが見つかりません",
  "MessageNoListeningSessions": "リスニングセッションなし",
  "MessageNoLogs": "ログなし",
  "MessageNoMediaProgress": "メディアの進捗状況なし",
  "MessageNoNotifications": "通知なし",
  "MessageNoPodcastFeed": "無効なポッドキャスト: フィードなし",
  "MessageNoPodcastsFound": "ポッドキャストが見つかりません",
  "MessageNoResults": "結果なし",
  "MessageNoSearchResultsFor": "\"{0}\" の検索結果はありません",
  "MessageNoSeries": "シリーズなし",
  "MessageNoTags": "タグなし",
  "MessageNoTasksRunning": "実行中のタスクなし",
  "MessageNoUpdatesWereNecessary": "更新は不要でした",
  "MessageNoUserPlaylists": "プレイリストがありません",
  "MessageNoUserPlaylistsHelp": "プレイリストは非公開です。作成したユーザーのみが見ることができます。",
  "MessageNotYetImplemented": "未実装",
  "MessageOpmlPreviewNote": "注: これは解析されたOPMLファイルのプレビューです。実際のポッドキャストタイトルはRSSフィードから取得されます。",
  "MessageOr": "または",
  "MessagePauseChapter": "チャプターの再生を一時停止",
  "MessagePlayChapter": "チャプターの最初から聴く",
  "MessagePlaylistCreateFromCollection": "コレクションからプレイリストを作成",
  "MessagePleaseWait": "しばらくお待ちください...",
  "MessagePodcastHasNoRSSFeedForMatching": "このポッドキャストには照合に使用できるRSSフィードURLがありません",
  "MessagePodcastSearchField": "検索キーワードまたはRSSフィードURLを入力",
  "MessageQuickEmbedInProgress": "クイック埋め込みを実行中",
  "MessageQuickEmbedQueue": "クイック埋め込みキューに追加されました(キュー内: {0}件)",
  "MessageQuickMatchAllEpisodes": "すべてのエピソードをクイックマッチ",
  "MessageQuickMatchDescription": "'{0}' の最初の一致結果でアイテムの空の詳細とカバーを設定します。サーバー設定の「一致したメタデータを優先」が有効な場合を除き、既存の詳細は上書きされません。",
  "MessageRemoveChapter": "チャプターを削除",
  "MessageRemoveEpisodes": "{0}件のエピソードを削除",
  "MessageRemoveFromPlayerQueue": "「次に再生」から削除",
  "MessageRemoveUserWarning": "ユーザー \"{0}\" を完全に削除してもよろしいですか？",
  "MessageReportBugsAndContribute": "バグ報告、機能リクエスト、コントリビューション:",
  "MessageResetChaptersConfirm": "チャプターをリセットして変更を元に戻してもよろしいですか？",
  "MessageRestoreBackupConfirm": "以下の日時に作成されたバックアップを復元してもよろしいですか：",
  "MessageRestoreBackupWarning": "バックアップを復元すると、/config にあるデータベース全体と /metadata/items および /metadata/authors のカバー画像が上書きされます。<br /><br />バックアップはライブラリーフォルダー内のファイルを変更しません。カバーアートとメタデータをライブラリーフォルダーに保存するサーバー設定を有効にしている場合、それらはバックアップされず上書きもされません。<br /><br />サーバーを使用しているすべてのクライアントは自動的に更新されます。",
  "MessageScheduleLibraryScanNote": "ほとんどのユーザーには、この機能を無効のままにして「ライブラリーの変更を自動的に監視する」設定を有効にしておくことをお勧めします。これによりライブラリーフォルダーの変更が自動的に検出されます。NFS などのファイルシステムで「ライブラリーの変更を自動的に監視する」が機能しない場合はこの機能を有効にしてください。",
  "MessageScheduleRunEveryWeekdayAtTime": "毎{0} {1} に実行",
  "MessageSearchResultsFor": "検索結果:",
  "MessageSelected": "{0}件選択中",
  "MessageSeriesSequenceCannotContainSpaces": "シリーズのシーケンスにスペースを含めることはできません",
  "MessageServerCouldNotBeReached": "サーバーに接続できませんでした",
  "MessageSetChaptersFromTracksDescription": "各オーディオファイルをチャプターとして設定し、チャプタータイトルにはファイル名を使用します",
  "MessageShareExpirationWillBe": "有効期限は <strong>{0}</strong> になります",
  "MessageShareExpiresIn": "{0} 後に期限切れ",
  "MessageShareURLWillBe": "共有URLは <strong>{0}</strong> になります",
  "MessageStartPlaybackAtTime": "\"{0}\" を {1} から再生しますか？",
  "MessageTaskAudioFileNotWritable": "オーディオファイル \"{0}\" は書き込み不可です",
  "MessageTaskCanceledByUser": "タスクがユーザーによりキャンセルされました",
  "MessageTaskDownloadingEpisodeDescription": "エピソード \"{0}\" をダウンロード中",
  "MessageTaskEmbeddingMetadata": "メタデータを埋め込み中",
  "MessageTaskEmbeddingMetadataDescription": "オーディオブック \"{0}\" にメタデータを埋め込み中",
  "MessageTaskEncodingM4b": "M4Bをエンコード中",
  "MessageTaskEncodingM4bDescription": "オーディオブック \"{0}\" を単一のm4bファイルにエンコード中",
  "MessageTaskFailed": "失敗",
  "MessageTaskFailedToBackupAudioFile": "オーディオファイル \"{0}\" のバックアップに失敗しました",
  "MessageTaskFailedToCreateCacheDirectory": "キャッシュディレクトリの作成に失敗しました",
  "MessageTaskFailedToEmbedMetadataInFile": "ファイル \"{0}\" へのメタデータ埋め込みに失敗しました",
  "MessageTaskFailedToMergeAudioFiles": "オーディオファイルのマージに失敗しました",
  "MessageTaskFailedToMoveM4bFile": "m4bファイルの移動に失敗しました",
  "MessageTaskFailedToWriteMetadataFile": "メタデータファイルの書き込みに失敗しました",
  "MessageTaskMatchingBooksInLibrary": "ライブラリー \"{0}\" の本を照合中",
  "MessageTaskNoFilesToScan": "スキャンするファイルがありません",
  "MessageTaskOpmlImport": "OPMLインポート",
  "MessageTaskOpmlImportDescription": "{0}件のRSSフィードからポッドキャストを作成中",
  "MessageTaskOpmlImportFeed": "OPMLインポートフィード",
  "MessageTaskOpmlImportFeedDescription": "RSSフィード \"{0}\" をインポート中",
  "MessageTaskOpmlImportFeedFailed": "ポッドキャストフィードの取得に失敗しました",
  "MessageTaskOpmlImportFeedPodcastDescription": "ポッドキャスト \"{0}\" を作成中",
  "MessageTaskOpmlImportFeedPodcastExists": "このパスにポッドキャストがすでに存在します",
  "MessageTaskOpmlImportFeedPodcastFailed": "ポッドキャストの作成に失敗しました",
  "MessageTaskOpmlImportFinished": "{0}件のポッドキャストを追加しました",
  "MessageTaskOpmlParseFailed": "OPMLファイルの解析に失敗しました",
  "MessageTaskOpmlParseFastFail": "無効なOPMLファイル: <opml> タグが見つからないか <outline> タグが見つかりません",
  "MessageTaskOpmlParseNoneFound": "OPMLファイルにフィードが見つかりません",
  "MessageTaskScanItemsAdded": "{0}件追加",
  "MessageTaskScanItemsMissing": "{0}件不明",
  "MessageTaskScanItemsUpdated": "{0}件更新",
  "MessageTaskScanNoChangesNeeded": "変更は不要でした",
  "MessageTaskScanningFileChanges": "\"{0}\" のファイル変更をスキャン中",
  "MessageTaskScanningLibrary": "\"{0}\" ライブラリーをスキャン中",
  "MessageTaskTargetDirectoryNotWritable": "ターゲットディレクトリは書き込み不可です",
  "MessageThinking": "処理中...",
  "MessageUploaderItemFailed": "アップロード失敗",
  "MessageUploaderItemSuccess": "アップロード成功！",
  "MessageUploading": "アップロード中...",
  "MessageValidCronExpression": "有効なCron式です",
  "MessageWatcherIsDisabledGlobally": "ウォッチャーはサーバー設定でグローバルに無効化されています",
  "MessageXLibraryIsEmpty": "{0} ライブラリーは空です！",
  "MessageYourAudiobookDurationIsLonger": "オーディオブックの長さが見つかった長さより長くなっています",
  "MessageYourAudiobookDurationIsShorter": "オーディオブックの長さが見つかった長さより短くなっています",
  "NoteChangeRootPassword": "ルートユーザーのみ空のパスワードを設定できます",
  "NoteChapterEditorTimes": "注: 最初のチャプターの開始時間は必ず0:00のままにしてください。また最後のチャプターの開始時間はオーディオブックの長さを超えることはできません。",
  "NoteFolderPicker": "注: すでにマッピング済みのフォルダーは表示されません",
  "NoteRSSFeedPodcastAppsHttps": "警告: ほとんどのポッドキャストアプリはHTTPSのRSSフィードURLが必要です",
  "NoteRSSFeedPodcastAppsPubDate": "警告: 1件以上のエピソードに公開日がありません。一部のポッドキャストアプリではこれが必要です。",
  "NoteUploaderFoldersWithMediaFiles": "メディアファイルを含むフォルダーは別々のライブラリーアイテムとして処理されます。",
  "NoteUploaderOnlyAudioFiles": "オーディオファイルのみをアップロードする場合、各オーディオファイルは個別のオーディオブックとして処理されます。",
  "NoteUploaderUnsupportedFiles": "サポートされていないファイルは無視されます。フォルダーを選択またはドロップする場合、アイテムフォルダー内にない他のファイルは無視されます。",
  "NotificationOnBackupCompletedDescription": "バックアップが完了したときにトリガーされます",
  "NotificationOnBackupFailedDescription": "バックアップが失敗したときにトリガーされます",
  "NotificationOnEpisodeDownloadedDescription": "ポッドキャストエピソードが自動ダウンロードされたときにトリガーされます",
  "NotificationOnRSSFeedDisabledDescription": "失敗が多すぎたため自動エピソードダウンロードが無効になったときにトリガーされます",
  "NotificationOnRSSFeedFailedDescription": "自動エピソードダウンロードのRSSフィードリクエストが失敗したときにトリガーされます",
  "NotificationOnTestDescription": "通知システムのテスト用イベント",
  "PlaceholderBulkChapterInput": "チャプタータイトルを入力するか、番号付けを使用(例: 「エピソード 1」「チャプター 10」「1.」)",
  "PlaceholderNewCollection": "新しいコレクション名",
  "PlaceholderNewFolderPath": "新しいフォルダーパス",
  "PlaceholderNewPlaylist": "新しいプレイリスト名",
  "PlaceholderSearch": "検索...",
  "PlaceholderSearchEpisode": "エピソードを検索...",
  "StatsAuthorsAdded": "追加された作者",
  "StatsBooksAdded": "追加された本",
  "StatsBooksAdditional": "その他の追加内容…",
  "StatsBooksFinished": "完了した本",
  "StatsBooksFinishedThisYear": "今年完了した本…",
  "StatsBooksListenedTo": "聴いた本",
  "StatsCollectionGrewTo": "あなたの本のコレクションが増えました…",
  "StatsSessions": "セッション",
  "StatsSpentListening": "リスニング時間",
  "StatsTopAuthor": "トップ作者",
  "StatsTopAuthors": "トップ作者",
  "StatsTopGenre": "トップジャンル",
  "StatsTopGenres": "トップジャンル",
  "StatsTopMonth": "トップ月",
  "StatsTopNarrator": "トップナレーター",
  "StatsTopNarrators": "トップナレーター",
  "StatsTotalDuration": "合計再生時間…",
  "StatsYearInReview": "年間振り返り",
  "ToastAccountUpdateSuccess": "アカウントを更新しました",
  "ToastAppriseUrlRequired": "Apprise URLを入力してください",
  "ToastAsinRequired": "ASINを入力してください",
  "ToastAuthorImageRemoveSuccess": "作者の画像を削除しました",
  "ToastAuthorNotFound": "作者「{0}」が見つかりません",
  "ToastAuthorRemoveSuccess": "作者を削除しました",
  "ToastAuthorSearchNotFound": "作者が見つかりません",
  "ToastAuthorUpdateMerged": "作者をマージしました",
  "ToastAuthorUpdateSuccess": "作者を更新しました",
  "ToastAuthorUpdateSuccessNoImageFound": "作者を更新しました(画像が見つかりません)",
  "ToastBackupAppliedSuccess": "バックアップを適用しました",
  "ToastBackupCreateFailed": "バックアップの作成に失敗しました",
  "ToastBackupCreateSuccess": "バックアップを作成しました",
  "ToastBackupDeleteFailed": "バックアップの削除に失敗しました",
  "ToastBackupDeleteSuccess": "バックアップを削除しました",
  "ToastBackupInvalidMaxKeep": "保持するバックアップ数が無効です",
  "ToastBackupInvalidMaxSize": "バックアップの最大サイズが無効です",
  "ToastBackupRestoreFailed": "バックアップの復元に失敗しました",
  "ToastBackupUploadFailed": "バックアップのアップロードに失敗しました",
  "ToastBackupUploadSuccess": "バックアップをアップロードしました",
  "ToastBatchApplyDetailsToItemsSuccess": "詳細をアイテムに適用しました",
  "ToastBatchDeleteFailed": "一括削除に失敗しました",
  "ToastBatchDeleteSuccess": "一括削除に成功しました",
  "ToastBatchQuickMatchFailed": "一括クイックマッチに失敗しました！",
  "ToastBatchQuickMatchStarted": "{0}冊の一括クイックマッチを開始しました！",
  "ToastBatchUpdateFailed": "一括更新に失敗しました",
  "ToastBatchUpdateSuccess": "一括更新に成功しました",
  "ToastBookmarkCreateFailed": "ブックマークの作成に失敗しました",
  "ToastBookmarkCreateSuccess": "ブックマークを追加しました",
  "ToastBookmarkRemoveSuccess": "ブックマークを削除しました",
  "ToastBulkChapterInvalidCount": "1〜150の数値を入力してください",
  "ToastCachePurgeFailed": "キャッシュのクリアに失敗しました",
  "ToastCachePurgeSuccess": "キャッシュをクリアしました",
  "ToastChapterLocked": "チャプターはロックされています。",
  "ToastChapterStartTimeAdjusted": "チャプター開始時間を{0}秒調整しました",
  "ToastChaptersAllLocked": "すべてのチャプターがロックされています。時間をシフトするにはいくつかのチャプターのロックを解除してください。",
  "ToastChaptersHaveErrors": "チャプターにエラーがあります",
  "ToastChaptersInvalidShiftAmountLast": "シフト量が無効です。最後のチャプターの開始時間がこのオーディオブックの長さを超えてしまいます。",
  "ToastChaptersInvalidShiftAmountStart": "シフト量が無効です。最初のチャプターがゼロまたは負の長さになり、2番目のチャプターに上書きされます。2番目のチャプターの開始時間を長くしてください。",
  "ToastChaptersMustHaveTitles": "チャプターにはタイトルが必要です",
  "ToastChaptersRemoved": "チャプターを削除しました",
  "ToastChaptersUpdated": "チャプターを更新しました",
  "ToastCollectionItemsAddFailed": "アイテムのコレクションへの追加に失敗しました",
  "ToastCollectionRemoveSuccess": "コレクションを削除しました",
  "ToastCollectionUpdateSuccess": "コレクションを更新しました",
  "ToastConnectionNotAvailable": "接続が利用できません。後でもう一度お試しください",
  "ToastCoverSearchFailed": "カバー検索に失敗しました",
  "ToastCoverUpdateFailed": "カバーの更新に失敗しました",
  "ToastDateTimeInvalidOrIncomplete": "日時が無効または不完全です",
  "ToastDeleteFileFailed": "ファイルの削除に失敗しました",
  "ToastDeleteFileSuccess": "ファイルを削除しました",
  "ToastDeviceAddFailed": "デバイスの追加に失敗しました",
  "ToastDeviceNameAlreadyExists": "その名前の電子書籍リーダー端末はすでに存在します",
  "ToastDeviceTestEmailFailed": "テストメールの送信に失敗しました",
  "ToastDeviceTestEmailSuccess": "テストメールを送信しました",
  "ToastEmailSettingsUpdateSuccess": "メール設定を更新しました",
  "ToastEncodeCancelFailed": "エンコードのキャンセルに失敗しました",
  "ToastEncodeCancelSucces": "エンコードをキャンセルしました",
  "ToastEpisodeDownloadQueueClearFailed": "ダウンロードキューのクリアに失敗しました",
  "ToastEpisodeDownloadQueueClearSuccess": "エピソードのダウンロードキューをクリアしました",
  "ToastEpisodeUpdateSuccess": "{0}個のエピソードを更新しました",
  "ToastErrorCannotShare": "このデバイスではネイティブ共有ができません",
  "ToastFailedToCreate": "作成に失敗しました",
  "ToastFailedToDelete": "削除に失敗しました",
  "ToastFailedToLoadData": "データの読み込みに失敗しました",
  "ToastFailedToMatch": "マッチングに失敗しました",
  "ToastFailedToShare": "共有に失敗しました",
  "ToastFailedToUpdate": "更新に失敗しました",
  "ToastInvalidImageUrl": "画像のURLが無効です",
  "ToastInvalidMaxEpisodesToDownload": "ダウンロード可能な最大エピソード数が無効です",
  "ToastInvalidUrl": "URLが無効です",
  "ToastInvalidUrls": "1つ以上のURLが無効です",
  "ToastItemCoverUpdateSuccess": "アイテムのカバーを更新しました",
  "ToastItemDeletedFailed": "アイテムの削除に失敗しました",
  "ToastItemDeletedSuccess": "アイテムを削除しました",
  "ToastItemDetailsUpdateSuccess": "アイテムの詳細を更新しました",
  "ToastItemMarkedAsFinishedFailed": "完了としてマークするのに失敗しました",
  "ToastItemMarkedAsFinishedSuccess": "アイテムを完了としてマークしました",
  "ToastItemMarkedAsNotFinishedFailed": "未完了としてマークするのに失敗しました",
  "ToastItemMarkedAsNotFinishedSuccess": "アイテムを未完了としてマークしました",
  "ToastItemUpdateSuccess": "アイテムを更新しました",
  "ToastLibraryCreateFailed": "ライブラリーの作成に失敗しました",
  "ToastLibraryCreateSuccess": "ライブラリー「{0}」を作成しました",
  "ToastLibraryDeleteFailed": "ライブラリーの削除に失敗しました",
  "ToastLibraryDeleteSuccess": "ライブラリーを削除しました",
  "ToastLibraryScanFailedToStart": "スキャンの開始に失敗しました",
  "ToastLibraryScanStarted": "ライブラリースキャンを開始しました",
  "ToastLibraryUpdateSuccess": "ライブラリー「{0}」を更新しました",
  "ToastMatchAllAuthorsFailed": "すべての作者のマッチングに失敗しました",
  "ToastMetadataFilesRemovedError": "metadata.{0}ファイルの削除中にエラーが発生しました",
  "ToastMetadataFilesRemovedNoneFound": "ライブラリー内にmetadata.{0}ファイルが見つかりません",
  "ToastMetadataFilesRemovedNoneRemoved": "削除されたmetadata.{0}ファイルはありません",
  "ToastMetadataFilesRemovedSuccess": "{0}個のmetadata.{1}ファイルを削除しました",
  "ToastMustHaveAtLeastOnePath": "少なくとも1つのパスが必要です",
  "ToastNameEmailRequired": "名前とメールアドレスが必要です",
  "ToastNameRequired": "名前を入力してください",
  "ToastNewApiKeyUserError": "ユーザーを選択してください",
  "ToastNewEpisodesFound": "{0}個の新しいエピソードが見つかりました",
  "ToastNewUserCreatedFailed": "アカウントの作成に失敗しました:「{0}」",
  "ToastNewUserCreatedSuccess": "新しいアカウントを作成しました",
  "ToastNewUserLibraryError": "少なくとも1つのライブラリーを選択してください",
  "ToastNewUserPasswordError": "パスワードが必要です。ルートユーザーのみ空のパスワードを使用できます",
  "ToastNewUserTagError": "少なくとも1つのタグを選択してください",
  "ToastNewUserUsernameError": "ユーザー名を入力してください",
  "ToastNoNewEpisodesFound": "新しいエピソードは見つかりません",
  "ToastNoRSSFeed": "ポッドキャストにはRSSフィードがありません",
  "ToastNoUpdatesNecessary": "更新の必要はありません",
  "ToastNotificationCreateFailed": "通知の作成に失敗しました",
  "ToastNotificationDeleteFailed": "通知の削除に失敗しました",
  "ToastNotificationFailedMaximum": "最大失敗試行回数は0以上である必要があります",
  "ToastNotificationQueueMaximum": "最大通知キューは0以上である必要があります",
  "ToastNotificationSettingsUpdateSuccess": "通知設定を更新しました",
  "ToastNotificationTestTriggerFailed": "テスト通知のトリガーに失敗しました",
  "ToastNotificationTestTriggerSuccess": "テスト通知をトリガーしました",
  "ToastNotificationUpdateSuccess": "通知を更新しました",
  "ToastPlaylistCreateFailed": "プレイリストの作成に失敗しました",
  "ToastPlaylistCreateSuccess": "プレイリストを作成しました",
  "ToastPlaylistRemoveSuccess": "プレイリストを削除しました",
  "ToastPlaylistUpdateSuccess": "プレイリストを更新しました",
  "ToastPodcastCreateFailed": "ポッドキャストの作成に失敗しました",
  "ToastPodcastCreateSuccess": "ポッドキャストを作成しました",
  "ToastPodcastEpisodeUpdated": "エピソードを更新しました",
  "ToastPodcastGetFeedFailed": "ポッドキャストフィードの取得に失敗しました",
  "ToastPodcastNoEpisodesInFeed": "RSSフィードにエピソードが見つかりません",
  "ToastPodcastNoRssFeed": "ポッドキャストにはRSSフィードがありません",
  "ToastProgressIsNotBeingSynced": "進捗が同期されていません。再生を再開してください",
  "ToastProviderCreatedFailed": "プロバイダーの追加に失敗しました",
  "ToastProviderCreatedSuccess": "新しいプロバイダーを追加しました",
  "ToastProviderNameAndUrlRequired": "名前とURLが必要です",
  "ToastProviderRemoveSuccess": "プロバイダーを削除しました",
  "ToastRSSFeedCloseFailed": "RSSフィードのクローズに失敗しました",
  "ToastRSSFeedCloseSuccess": "RSSフィードをクローズしました",
  "ToastRemoveFailed": "削除に失敗しました",
  "ToastRemoveItemFromCollectionFailed": "コレクションからのアイテム削除に失敗しました",
  "ToastRemoveItemFromCollectionSuccess": "アイテムをコレクションから削除しました",
  "ToastRemoveItemsWithIssuesFailed": "問題のあるライブラリーアイテムの削除に失敗しました",
  "ToastRemoveItemsWithIssuesSuccess": "問題のあるライブラリーアイテムを削除しました",
  "ToastRenameFailed": "名前変更に失敗しました",
  "ToastRescanFailed": "{0}の再スキャンに失敗しました",
  "ToastRescanRemoved": "再スキャンが完了しました。アイテムが削除されました",
  "ToastRescanUpToDate": "再スキャンが完了しました。アイテムは最新です",
  "ToastRescanUpdated": "再スキャンが完了しました。アイテムが更新されました",
  "ToastScanFailed": "ライブラリーアイテムのスキャンに失敗しました",
  "ToastSelectAtLeastOneUser": "少なくとも1人のユーザーを選択してください",
  "ToastSendEbookToDeviceFailed": "電子書籍のデバイスへの送信に失敗しました",
  "ToastSendEbookToDeviceSuccess": "電子書籍をデバイス「{0}」に送信しました",
  "ToastSeriesSubmitFailedSameName": "同じ名前のシリーズを2つ追加することはできません",
  "ToastSeriesUpdateFailed": "シリーズの更新に失敗しました",
  "ToastSeriesUpdateSuccess": "シリーズを更新しました",
  "ToastServerSettingsUpdateSuccess": "サーバー設定を更新しました",
  "ToastSessionCloseFailed": "セッションのクローズに失敗しました",
  "ToastSessionDeleteFailed": "セッションの削除に失敗しました",
  "ToastSessionDeleteSuccess": "セッションを削除しました",
  "ToastSleepTimerDone": "スリープタイマーが終了しました... zZzzZz",
  "ToastSlugMustChange": "スラグに無効な文字が含まれています",
  "ToastSlugRequired": "スラグを入力してください",
  "ToastSocketConnected": "ソケットが接続されました",
  "ToastSocketDisconnected": "ソケットが切断されました",
  "ToastSocketFailedToConnect": "ソケット接続に失敗しました",
  "ToastSortingPrefixesEmptyError": "少なくとも1つのソート接頭辞が必要です",
  "ToastSortingPrefixesUpdateSuccess": "ソート接頭辞を更新しました({0}アイテム)",
  "ToastTitleRequired": "タイトルを入力してください",
  "ToastUnknownError": "不明なエラー",
  "ToastUnlinkOpenIdFailed": "OpenIDからのユーザーのリンク解除に失敗しました",
  "ToastUnlinkOpenIdSuccess": "ユーザーをOpenIDからリンク解除しました",
  "ToastUploaderFilepathExistsError": "ファイルパス「{0}」はサーバーにすでに存在しています",
  "ToastUploaderItemExistsInSubdirectoryError": "アイテム「{0}」はアップロードパスのサブディレクトリーを使用しています。",
  "ToastUserDeleteFailed": "ユーザーの削除に失敗しました",
  "ToastUserDeleteSuccess": "ユーザーを削除しました",
  "ToastUserPasswordChangeSuccess": "パスワードを変更しました",
  "ToastUserPasswordMismatch": "パスワードが一致しません",
  "ToastUserPasswordMustChange": "新しいパスワードは古いパスワードと同じにすることはできません",
  "ToastUserRootRequireName": "ルートユーザー名を入力してください",
  "TooltipAddChapters": "チャプターを追加",
  "TooltipAddOneSecond": "1秒追加",
  "TooltipAdjustChapterStart": "クリックして開始時刻を調整",
  "TooltipLockAllChapters": "すべてのチャプターをロック",
  "TooltipLockChapter": "チャプターをロック(Shift+クリックで範囲選択)",
  "TooltipSubtractOneSecond": "1秒減算",
  "TooltipUnlockAllChapters": "すべてのチャプターをロック解除",
  "TooltipUnlockChapter": "チャプターをロック解除(Shift+クリックで範囲選択)"
}
